pytestskipmarkers/__init__.py
pytestskipmarkers/plugin.py
pytestskipmarkers/py.typed
pytestskipmarkers/version.py
pytestskipmarkers/utils/__init__.py
pytestskipmarkers/utils/markers.py
pytestskipmarkers/utils/platform.py
pytestskipmarkers/utils/ports.py
pytestskipmarkers/utils/socket.py
pytestskipmarkers/utils/socket.pyi
pytestskipmarkers/utils/win_functions.py
pytest_skip_markers-1.5.2.dist-info/LICENSE
pytest_skip_markers-1.5.2.dist-info/METADATA
pytest_skip_markers-1.5.2.dist-info/NOTICE
pytest_skip_markers-1.5.2.dist-info/WHEEL
pytest_skip_markers-1.5.2.dist-info/entry_points.txt
pytest_skip_markers-1.5.2.dist-info/top_level.txt
pytest_skip_markers-1.5.2.dist-info/RECORD
