Metadata-Version: 2.1
Name: pytest-skip-markers
Version: 1.5.2
Summary: Pytest Salt Plugin
Home-page: https://github.com/saltstack/pytest-skip-markers
Author: Pedro Algarvio
Author-email: pedro@algarvio.me
License: Apache Software License 2.0
Project-URL: Source, https://github.com/saltstack/pytest-skip-markers
Project-URL: Tracker, https://github.com/saltstack/pytest-skip-markers/issues
Project-URL: Documentation, https://pytest-skip-markers.readthedocs.io
Platform: unix
Platform: linux
Platform: osx
Platform: cygwin
Platform: win32
Classifier: Programming Language :: Python
Classifier: Programming Language :: Cython
Classifier: Programming Language :: Python :: 3
Classifier: Programming Language :: Python :: 3 :: Only
Classifier: Programming Language :: Python :: 3.8
Classifier: Programming Language :: Python :: 3.9
Classifier: Programming Language :: Python :: 3.10
Classifier: Programming Language :: Python :: 3.11
Classifier: Programming Language :: Python :: 3.12
Classifier: Development Status :: 5 - Production/Stable
Classifier: Framework :: Pytest
Classifier: Typing :: Typed
Classifier: Intended Audience :: Developers
Classifier: License :: OSI Approved :: Apache Software License
Requires-Python: >=3.8
License-File: LICENSE
License-File: NOTICE
Requires-Dist: pytest >=7.1.0
Requires-Dist: attrs >=19.2.0
Requires-Dist: distro
Requires-Dist: pywin32 ; sys_platform == "win32"
Provides-Extra: changelog
Requires-Dist: towncrier ==21.9.0rc1 ; extra == 'changelog'
Provides-Extra: docker
Requires-Dist: docker ; extra == 'docker'
Provides-Extra: docs
Requires-Dist: furo ; extra == 'docs'
Requires-Dist: sphinx ; extra == 'docs'
Requires-Dist: sphinx-copybutton ; extra == 'docs'
Requires-Dist: sphinx-prompt ; extra == 'docs'
Requires-Dist: sphinxcontrib-spelling ; extra == 'docs'
Requires-Dist: sphinxcontrib-towncrier >=0.2.1a0 ; extra == 'docs'
Provides-Extra: lint
Requires-Dist: pylint ==2.12.2 ; extra == 'lint'
Requires-Dist: pyenchant ; extra == 'lint'
Requires-Dist: flake8 >=4.0.1 ; extra == 'lint'
Requires-Dist: flake8-mypy-fork ; extra == 'lint'
Requires-Dist: flake8-docstrings ; extra == 'lint'
Requires-Dist: flake8-typing-imports ; extra == 'lint'
Requires-Dist: black ; (python_version >= "3.8") and extra == 'lint'
Requires-Dist: reorder-python-imports ; (python_version >= "3.8") and extra == 'lint'
Provides-Extra: salt
Requires-Dist: salt >=3001 ; extra == 'salt'
Provides-Extra: tests
Requires-Dist: docker ; extra == 'tests'
Requires-Dist: pytest-subtests ; extra == 'tests'
Requires-Dist: cryptography ; extra == 'tests'
Requires-Dist: pyfakefs ==4.4.0 ; (python_version == "3.5") and extra == 'tests'
Requires-Dist: pyfakefs ; (python_version > "3.5") and extra == 'tests'
